quickshell/__init__.py
quickshell/py.typed
quickshell/shell.py
quickshell-1.3.0.dist-info/METADATA
quickshell-1.3.0.dist-info/WHEEL
quickshell-1.3.0.dist-info/licenses/LICENSE
quickshell-1.3.0.dist-info/RECORD
