Metadata-Version: 2.4
Name: quickshell
Version: 1.3.0
Summary: Removes the boilierplate when working with shells in python.
Author: Aaron2599
License-File: LICENSE
Requires-Python: >=3.8
